django_suit_locale-1.0.10.dist-info/DESCRIPTION.rst
django_suit_locale-1.0.10.dist-info/METADATA
django_suit_locale-1.0.10.dist-info/metadata.json
django_suit_locale-1.0.10.dist-info/RECORD
django_suit_locale-1.0.10.dist-info/top_level.txt
django_suit_locale-1.0.10.dist-info/WHEEL
suitlocale/__init__.py
suitlocale/locale/cs/LC_MESSAGES/django.mo
suitlocale/locale/cs/LC_MESSAGES/django.po
suitlocale/locale/en/LC_MESSAGES/django.mo
suitlocale/locale/en/LC_MESSAGES/django.po
suitlocale/locale/es/LC_MESSAGES/django.mo
suitlocale/locale/es/LC_MESSAGES/django.po
suitlocale/locale/es_AR/LC_MESSAGES/django.mo
suitlocale/locale/es_AR/LC_MESSAGES/django.po
suitlocale/locale/fr/LC_MESSAGES/django.mo
suitlocale/locale/fr/LC_MESSAGES/django.po
suitlocale/locale/pl/LC_MESSAGES/django.mo
suitlocale/locale/pl/LC_MESSAGES/django.po
suitlocale/locale/pt_BR/LC_MESSAGES/django.mo
suitlocale/locale/pt_BR/LC_MESSAGES/django.po
suitlocale/locale/ru/LC_MESSAGES/django.mo
suitlocale/locale/ru/LC_MESSAGES/django.po
suitlocale/locale/sk/LC_MESSAGES/django.mo
suitlocale/locale/sk/LC_MESSAGES/django.po
suitlocale/locale/tr/LC_MESSAGES/django.mo
suitlocale/locale/tr/LC_MESSAGES/django.po
